mindtrace/cluster/__init__.py
mindtrace/cluster/core/cluster.py
mindtrace/cluster/core/dlq.py
mindtrace/cluster/core/types.py
mindtrace/cluster/workers/echo_worker.py
mindtrace/cluster/workers/run_script_worker.py
mindtrace/cluster/workers/environments/docker_env.py
mindtrace/cluster/workers/environments/git_env.py
mindtrace_cluster-0.8.0.dist-info/licenses/LICENSE
mindtrace_cluster-0.8.0.dist-info/METADATA
mindtrace_cluster-0.8.0.dist-info/WHEEL
mindtrace_cluster-0.8.0.dist-info/top_level.txt
mindtrace_cluster-0.8.0.dist-info/RECORD
